{
	"name": "intro",
	"layers": [
		{
			"name": "background",
			"overriden": 0,
			"subLayers": [],
			"instances": [],
			"sid": 833653987764235,
			"effectTypes": [],
			"isInitiallyVisible": true,
			"isInitiallyInteractive": true,
			"color": [
				1,
				1,
				1,
				1
			],
			"backgroundColor": [
				0,
				0,
				0,
				1
			],
			"isTransparent": false,
			"parallaxX": 1,
			"parallaxY": 1,
			"scaleRate": 1,
			"forceOwnTexture": false,
			"renderingMode": "2d",
			"drawOrder": "z-order",
			"useRenderCells": false,
			"blendMode": "normal",
			"zElevation": 0,
			"global": false
		},
		{
			"name": "cutscene-dialogic",
			"overriden": 0,
			"subLayers": [],
			"instances": [
				{
					"type": "dialog",
					"properties": {
						"text": "...",
						"enable-bbcode": true,
						"font": "pixel",
						"size": 16,
						"line-height": 0,
						"bold": false,
						"italic": false,
						"color": [
							1,
							1,
							1,
							1
						],
						"horizontal-alignment": "center",
						"vertical-alignment": "center",
						"wrapping": "word",
						"initially-visible": true,
						"origin": "top-left"
					},
					"uid": 436,
					"instanceVariables": {},
					"behaviors": {
						"Timer": {
							"properties": {}
						}
					},
					"world": {
						"x": 1,
						"y": 350,
						"width": 640,
						"height": 128,
						"originX": 0,
						"originY": 0,
						"color": [
							1,
							1,
							1,
							1
						],
						"angle": 0,
						"zElevation": 0
					}
				}
			],
			"sid": 985115840662503,
			"effectTypes": [],
			"isInitiallyVisible": true,
			"isInitiallyInteractive": true,
			"color": [
				1,
				1,
				1,
				1
			],
			"backgroundColor": [
				1,
				1,
				1,
				1
			],
			"isTransparent": true,
			"parallaxX": 0,
			"parallaxY": 0,
			"scaleRate": 1,
			"forceOwnTexture": false,
			"renderingMode": "2d",
			"drawOrder": "z-order",
			"useRenderCells": false,
			"blendMode": "normal",
			"zElevation": 0,
			"global": false
		}
	],
	"sid": 646417385062411,
	"nonworld-instances": [],
	"effectTypes": [],
	"width": 640,
	"height": 480,
	"unboundedScrolling": false,
	"vpX": 0.5,
	"vpY": 0.5,
	"projection": "perspective",
	"eventSheet": "#Cutscene"
}